contiamo/__init__.py
contiamo/data.py
contiamo/dateparser.py
contiamo/errors.py
contiamo/http_client.py
contiamo/public.py
contiamo/resources.py
contiamo/utils.py
contiamo/version.py
contiamo/tests/__init__.py
contiamo/tests/test_class_nesting.py
contiamo/tests/test_dateparser.py
contiamo/tests/test_errors.py
contiamo/tests/test_jsonparser.py
contiamo/tests/test_requests.py
contiamo/tests/test_resources.py
contiamo/tests/test_url_generation.py
contiamo/tests/utils.py
contiamo-0.1.3.dist-info/LICENSE
contiamo-0.1.3.dist-info/METADATA
contiamo-0.1.3.dist-info/WHEEL
contiamo-0.1.3.dist-info/top_level.txt
contiamo-0.1.3.dist-info/RECORD
