Metadata-Version: 2.1
Name: contiamo
Version: 0.1.3
Summary: Contiamo Python client
Home-page: https://github.com/contiamo/contiamo-client-python
Author: Contiamo
Author-email: support@contiamo.com
License: UNKNOWN
Platform: UNKNOWN
Classifier: Development Status :: 5 - Production/Stable
Classifier: Intended Audience :: Developers
Classifier: License :: OSI Approved :: MIT License
Classifier: Operating System :: OS Independent
Classifier: Programming Language :: Python
Classifier: Programming Language :: Python :: 3
Classifier: Programming Language :: Python :: 3.2
Classifier: Programming Language :: Python :: 3.3
Classifier: Programming Language :: Python :: 3.4
Classifier: Programming Language :: Python :: 3.5
Classifier: Programming Language :: Python :: Implementation :: PyPy
Classifier: Topic :: Software Development :: Libraries :: Python Modules
Requires-Dist: isoweek (>=1.3.3)
Requires-Dist: numpy (>=1.14.1)
Requires-Dist: pandas (>=0.22.0)
Requires-Dist: pip (>=19.0)
Requires-Dist: requests (>=2.20)
